CHANGES.txt
CONTRIBUTORS.txt
README.txt
bootstrap.py
buildout.cfg
setup.cfg
setup.py
topp/__init__.py
topp.recipes.opvarnish.egg-info/PKG-INFO
topp.recipes.opvarnish.egg-info/SOURCES.txt
topp.recipes.opvarnish.egg-info/dependency_links.txt
topp.recipes.opvarnish.egg-info/entry_points.txt
topp.recipes.opvarnish.egg-info/namespace_packages.txt
topp.recipes.opvarnish.egg-info/not-zip-safe
topp.recipes.opvarnish.egg-info/paster_plugins.txt
topp.recipes.opvarnish.egg-info/requires.txt
topp.recipes.opvarnish.egg-info/top_level.txt
topp/recipes/__init__.py
topp/recipes/opvarnish/README.txt
topp/recipes/opvarnish/__init__.py
topp/recipes/opvarnish/myvarnish.py
topp/recipes/opvarnish/template.vcl
topp/recipes/opvarnish/tests/__init__.py
topp/recipes/opvarnish/tests/test_docs.py