Metadata-Version: 1.0
Name: topp.recipes.opvarnish
Version: 0.1.0dev-r19447
Summary: OpenPlans varnish caching server configuration
Home-page: http://topp.openplans.org/
Author: TOPP
Author-email: info@openplans.org
License: GPLv3
Platform: UNKNOWN
Classifier: Framework :: Buildout
Classifier: Intended Audience :: Developers
Classifier: Topic :: Software Development :: Build Tools
Classifier: Topic :: Software Development :: Libraries :: Python Modules
